CHANGES.rst
LICENSE.rst
README.rst
setup.py
etc/redis.conf
etc/redis.tiger.patch
src/torque/__init__.py
src/torque/client.py
src/torque/processor.py
src/torque/run.py
src/torque/utils.py
src/torque/webapp.py
src/torque.egg-info/PKG-INFO
src/torque.egg-info/SOURCES.txt
src/torque.egg-info/dependency_links.txt
src/torque.egg-info/entry_points.txt
src/torque.egg-info/not-zip-safe
src/torque.egg-info/requires.txt
src/torque.egg-info/top_level.txt
vendor/redis-git
vendor/tornado-git