Metadata-Version: 1.0
Name: torque
Version: 0.4.3
Summary: A web hook task queue based on tornado and redis
Home-page: http://github.com/thruflo/torque
Author: James Arthur
Author-email: thruflo@googlemail.com
License: Creative Commons CC0 1.0 Universal
Platform: UNKNOWN
Classifier: Development Status :: 3 - Alpha
Classifier: Environment :: Web Environment
Classifier: Intended Audience :: Developers
Classifier: License :: Public Domain
Classifier: Programming Language :: Python
